HT/__init__.py
HT/band_structure.py
HT/butterfly.py
HT/configuration/__init__.py
HT/configuration/hopping_input.txt
HT/functions/__init__.py
HT/functions/arguments.py
HT/functions/band_structure.py
HT/functions/butterfly.py
HT/functions/models.py
HT/functions/plotting.py
HT/functions/utility.py
HT/models/__init__.py
HT/models/hofstadter.py
HT/plot/__init__.py
HT/plot/plot_band_structure.py
HT/plot/plot_butterfly.py
HT/tests/__init__.py
HT/tests/conftest.py
HT/tests/test_band_structure.py
HT/tests/test_butterfly.py
HT/tests/band_structure/__init__.py
HT/tests/band_structure/band_structure_3D_bravais_nphi_1_5_t_0.5_0.2_alpha_1_theta_67_180_samp_11.npz
HT/tests/band_structure/band_structure_3D_honeycomb_nphi_1_5_t_1_alpha_1_theta_1_3_samp_11.npz
HT/tests/band_structure/band_structure_3D_kagome_nphi_1_5_t_1_alpha_1_theta_1_3_period_8_samp_11.npz
HT/tests/band_structure/band_structure_3D_square_nphi_1_5_t_1_0_-0.25_samp_11.npz
HT/tests/band_structure/band_structure_3D_square_nphi_1_5_t_1_samp_11.npz
HT/tests/band_structure/band_structure_3D_triangular_nphi_1_5_t_0_1_period_2_samp_11.npz
HT/tests/band_structure/band_structure_3D_triangular_nphi_1_5_t_1_samp_11.npz
HT/tests/butterfly/__init__.py
HT/tests/butterfly/butterfly_bravais_q_97_t_0.5_0.2_alpha_1_theta_67_180.npz
HT/tests/butterfly/butterfly_honeycomb_q_97_t_1_alpha_1_theta_1_3.npz
HT/tests/butterfly/butterfly_kagome_q_97_t_1_alpha_1_theta_1_3_period_8.npz
HT/tests/butterfly/butterfly_square_q_97_t_1.npz
HT/tests/butterfly/butterfly_square_q_97_t_1_0_-0.25.npz
HT/tests/butterfly/butterfly_triangular_q_97_t_0_1_period_2.npz
HT/tests/butterfly/butterfly_triangular_q_97_t_1.npz
HofstadterTools-1.0.4.dist-info/LICENSE
HofstadterTools-1.0.4.dist-info/METADATA
HofstadterTools-1.0.4.dist-info/WHEEL
HofstadterTools-1.0.4.dist-info/entry_points.txt
HofstadterTools-1.0.4.dist-info/top_level.txt
HofstadterTools-1.0.4.dist-info/RECORD
