Metadata-Version: 2.1
Name: HofstadterTools
Version: 1.0.4
Summary: A Python package for analyzing the Hofstadter model.
Author-email: Bartholomew Andrews <bartandrews123@gmail.com>
Maintainer-email: Bartholomew Andrews <bartandrews123@gmail.com>
License: GNU GENERAL PUBLIC LICENSE
Project-URL: Homepage, https://hofstadter.tools
Project-URL: Paper, https://doi.org/10.21105/joss.06356
Project-URL: Documentation, https://hofstadter.tools
Project-URL: Repository, https://github.com/HofstadterTools/HofstadterTools
Project-URL: Issues, https://github.com/HofstadterTools/HofstadterTools/issues
Keywords: theoretical-physics,electromagnetism,fractals,quantum-physics,topological-materials,mathematical-physics,topological-order,condensed-matter-physics,quantum-hall-effect,band-theory
Classifier: Development Status :: 5 - Production/Stable
Classifier: Environment :: Console
Classifier: Intended Audience :: Science/Research
Classifier: Intended Audience :: Education
Classifier: License :: OSI Approved :: GNU General Public License v3 (GPLv3)
Classifier: Natural Language :: English
Classifier: Operating System :: OS Independent
Classifier: Programming Language :: Python :: 3
Classifier: Topic :: Education
Classifier: Topic :: Scientific/Engineering :: Mathematics
Classifier: Topic :: Scientific/Engineering :: Physics
Requires-Python: >=3.9
License-File: LICENSE
Requires-Dist: numpy
Requires-Dist: matplotlib
Requires-Dist: prettytable
Requires-Dist: tqdm
Requires-Dist: pytest
Requires-Dist: ipython
Requires-Dist: jupyter
Requires-Dist: PyQt5
Provides-Extra: docs
Requires-Dist: sphinx ==5.3.0 ; extra == 'docs'
Requires-Dist: sphinx-rtd-theme ; extra == 'docs'
Requires-Dist: sphinxcontrib-bibtex ==2.5.0 ; extra == 'docs'
Requires-Dist: sphinx-copybutton ; extra == 'docs'
Requires-Dist: pydata-sphinx-theme ; extra == 'docs'
Requires-Dist: sphinx-autodoc-typehints ==1.19.5 ; extra == 'docs'
Requires-Dist: nbsphinx ; extra == 'docs'
Requires-Dist: graphviz ; extra == 'docs'
Requires-Dist: pybtex ; extra == 'docs'
Requires-Dist: jupytext ; extra == 'docs'
Requires-Dist: pypandoc ; extra == 'docs'
Requires-Dist: myst-parser ; extra == 'docs'
Requires-Dist: tomli ; extra == 'docs'
